zumi_AI/__init__.py
zumi_AI/face_recognizer.py
zumi_AI/protocol.py
zumi_AI/receiver.py
zumi_AI/serial_class.py
zumi_AI/sketch_recognizer.py
zumi_AI/socket_class.py
zumi_AI/zumi_AI.py
zumi_AI/res/model/face_detector.tflite
zumi_AI/res/model/face_keypoints.tflite
zumi_AI/res/model/face_recognizer.tflite
zumi_AI/res/model/iris_landmark.tflite
zumi_AI/res/model/mnist_model.tflite
zumi_ai-0.1.24.dist-info/licenses/LICENSE
zumi_ai-0.1.24.dist-info/METADATA
zumi_ai-0.1.24.dist-info/WHEEL
zumi_ai-0.1.24.dist-info/top_level.txt
zumi_ai-0.1.24.dist-info/RECORD
