Metadata-Version: 2.4
Name: zumi-ai
Version: 0.1.24
Summary: Zumi AI for library.
Author-email: dr <drlee@robolink.co.kr>
License-Expression: MIT
Project-URL: Homepage, https://github.com/truedo/zumi_mini_python_backup
Project-URL: Bug Tracker, https://github.com/truedo/zumi_mini_python_backup/issues
Keywords: ai,zumi,robotics
Classifier: Programming Language :: Python :: 3
Classifier: Operating System :: OS Independent
Requires-Python: >=3.9
License-File: LICENSE
Requires-Dist: colorama==0.4.6
Requires-Dist: pynput==1.8.1
Requires-Dist: pyserial==3.5
Provides-Extra: pro
Requires-Dist: mediapipe==0.10.21; extra == "pro"
Requires-Dist: numpy==1.26.4; extra == "pro"
Requires-Dist: opencv-contrib-python==4.6.0.66; extra == "pro"
Requires-Dist: pupil-apriltags==1.0.4.post11; extra == "pro"
Requires-Dist: tensorflow==2.19.0; extra == "pro"
Requires-Dist: ultralytics==8.3.100; extra == "pro"
Requires-Dist: websocket-client==1.8.0; extra == "pro"
Dynamic: license-file
